odoo10_addon_base_ir_filters_company-10.0.1.0.0.99.dev2-py3.6-nspkg.pth
odoo/addons/base_ir_filters_company/README.rst
odoo/addons/base_ir_filters_company/__init__.py
odoo/addons/base_ir_filters_company/__manifest__.py
odoo/addons/base_ir_filters_company/post_install.py
odoo/addons/base_ir_filters_company/i18n/base_ir_filters_company.pot
odoo/addons/base_ir_filters_company/models/__init__.py
odoo/addons/base_ir_filters_company/models/ir_filters.py
odoo/addons/base_ir_filters_company/security/base_ir_filters_company_security.xml
odoo/addons/base_ir_filters_company/static/description/icon.png
odoo/addons/base_ir_filters_company/views/ir_filters.xml
odoo10_addon_base_ir_filters_company-10.0.1.0.0.99.dev2.dist-info/METADATA
odoo10_addon_base_ir_filters_company-10.0.1.0.0.99.dev2.dist-info/WHEEL
odoo10_addon_base_ir_filters_company-10.0.1.0.0.99.dev2.dist-info/namespace_packages.txt
odoo10_addon_base_ir_filters_company-10.0.1.0.0.99.dev2.dist-info/top_level.txt
odoo10_addon_base_ir_filters_company-10.0.1.0.0.99.dev2.dist-info/RECORD
